{
  "general": {
    "fontFamily": "'Libre Franklin', sans-serif",
    "textTransform": "uppercase"
  },
  "name": "Golett buttons",
  "settings": {
    "primary": {
      "default": {
        "bg": {
          "color": [
            "transparent",
            "transparent"
          ]
        },
        "border": {
          "color": [
            "brand",
            "brand"
          ]
        },
        "color": [
          "brand",
          "brand"
        ],
        "fontWeight": 600
      },
      "hover": {
        "bg": {
          "color": [
            "transparent",
            "transparent"
          ]
        },
        "color": [
          "brand?saturate=-1.31&lighten=-10.2",
          "lightShade"
        ],
        "fontWeight": 600,
        "border": {
          "color": [
            "brand?saturate=-1.31&lighten=-10.2",
            "lightShade"
          ]
        }
      }
    },
    "secondary": {
      "default": {
        "bg": {
          "color": [
            "transparent",
            "lightShade"
          ]
        },
        "border": {
          "color": [
            "darkShade?saturate=3.33&lighten=88.24&spin=240",
            "transparent"
          ]
        },
        "color": [
          "darkShade",
          "brand"
        ],
        "fontWeight": 600
      },
      "hover": {
        "bg": {
          "color": [
            "transparent",
            "lightShade"
          ]
        },
        "color": [
          "darkShade?lighten=52.94",
          "darkShade"
        ],
        "fontWeight": 600
      }
    },
    "primaryAlt": {
      "default": {
        "bg": {
          "color": [
            "transparent",
            "transparent"
          ]
        },
        "border": {
          "color": [
            "brand",
            "brand"
          ]
        },
        "color": [
          "brand",
          "brand"
        ],
        "fontWeight": 600
      },
      "hover": {
        "bg": {
          "color": [
            "transparent",
            "transparent"
          ]
        },
        "color": [
          "brand?saturate=-1.31&lighten=-10.2",
          "lightShade"
        ],
        "fontWeight": 600,
        "border": {
          "color": [
            "brand?saturate=-1.31&lighten=-10.2",
            "lightShade"
          ]
        }
      }
    },
    "secondaryAlt": {
      "default": {
        "bg": {
          "color": [
            "transparent",
            "lightShade"
          ]
        },
        "border": {
          "color": [
            "darkShade?saturate=3.33&lighten=88.24&spin=240",
            "transparent"
          ]
        },
        "color": [
          "darkShade",
          "brand"
        ],
        "fontWeight": 600
      },
      "hover": {
        "bg": {
          "color": [
            "transparent",
            "lightShade"
          ]
        },
        "color": [
          "darkShade?lighten=52.94",
          "darkShade"
        ],
        "border": {
          "color": [
            "darkShade?lighten=52.94",
            "transparent"
          ]
        },
        "fontWeight": 600
      }
    }
  },
  "size": {
    "lg": {
      "borderRadius": "3px",
      "borderWidth": "1px",
      "fontSize": "16px",
      "padding": "18px 29px 18px 29px"
    },
    "md": {
      "borderRadius": "3px",
      "borderWidth": "1px",
      "fontSize": "14px",
      "padding": "15px 20px 15px 20px"
    },
    "sm": {
      "borderRadius": "3px",
      "borderWidth": "1px",
      "fontSize": "14px",
      "padding": "12px 16px 12px 16px"
    }
  }
}